python_cli_base/__init__.py
python_cli_base/__main__.py
python_cli_base-0.0.2.dist-info/METADATA
python_cli_base-0.0.2.dist-info/WHEEL
python_cli_base-0.0.2.dist-info/entry_points.txt
python_cli_base-0.0.2.dist-info/licenses/LICENSE
python_cli_base-0.0.2.dist-info/RECORD
