Metadata-Version: 2.1
Name: python-cli-base
Version: 0.0.2
Summary: Base python cli project
Project-URL: homepage, https://github.com/jujumilk3/python-cli-base
Project-URL: bug-tracker, https://github.com/jujumilk3/python-cli-base/issues
Author-email: gyudoza <jujumilk3@gmail.com>
License-File: LICENSE
Classifier: License :: OSI Approved :: MIT License
Classifier: Operating System :: OS Independent
Classifier: Programming Language :: Python :: 3
Requires-Python: >=3.6
Requires-Dist: click
